geniushub_client-0.7.2.dist-info/licenses/LICENSE
geniushubclient/__init__.py
geniushubclient/_version.py
geniushubclient/const.py
geniushubclient/device.py
geniushubclient/issue.py
geniushubclient/session.py
geniushubclient/zone.py
tests/__init__.py
tests/data_properties_v3_conversion/__init__.py
tests/data_properties_v3_conversion/genius_zone_data_footprint_schedule_test.py
tests/data_properties_v3_conversion/genius_zone_data_is_occupied_test.py
tests/data_properties_v3_conversion/genius_zone_data_override_test.py
tests/data_properties_v3_conversion/genius_zone_data_properties_test.py
tests/data_properties_v3_conversion/genius_zone_data_state_test.py
tests/data_properties_v3_conversion/genius_zone_data_test.py
tests/data_properties_v3_conversion/genius_zone_data_timer_schedule_test.py
tests/issues_v3_conversion/__init__.py
tests/issues_v3_conversion/genius_issue_data_test.py
geniushub_client-0.7.2.dist-info/METADATA
geniushub_client-0.7.2.dist-info/WHEEL
geniushub_client-0.7.2.dist-info/top_level.txt
geniushub_client-0.7.2.dist-info/RECORD
