Metadata-Version: 2.4
Name: geniushub-client
Version: 0.7.2
Summary: An aiohttp-based client for Genius Hub systems
Home-page: https://github.com/manzanotti/geniushub-client
Author: Paul Manzotti
Author-email: manzo@gorilla-tactics.com
License: MIT
Project-URL: Bug Reports, https://github.com/manzanotti/geniushub-client/issues
Project-URL: Source, https://github.com/manzanotti/geniushub-client
Keywords: genius,geniushub,heatgenius
Classifier: Development Status :: 4 - Beta
Classifier: License :: OSI Approved :: MIT License
Classifier: Operating System :: OS Independent
Classifier: Programming Language :: Python :: 3.7
Classifier: Topic :: Home Automation
Requires-Python: >=3.9
License-File: LICENSE
Requires-Dist: aiohttp
Dynamic: author
Dynamic: author-email
Dynamic: classifier
Dynamic: description
Dynamic: description-content-type
Dynamic: home-page
Dynamic: keywords
Dynamic: license
Dynamic: license-file
Dynamic: project-url
Dynamic: requires-dist
Dynamic: requires-python
Dynamic: summary
